sage/_version.py
isage-0.2.3.3.dist-info/METADATA
isage-0.2.3.3.dist-info/WHEEL
isage-0.2.3.3.dist-info/top_level.txt
isage-0.2.3.3.dist-info/RECORD
