Metadata-Version: 2.4
Name: isage
Version: 0.2.3.3
Summary: SAGE - Streaming-Augmented Generative Execution
Author-email: SAGE Team <shuhao_zhang@hust.edu.cn>
License-Expression: MIT
Project-URL: Homepage, https://github.com/intellistream/SAGE
Project-URL: Documentation, https://intellistream.github.io/SAGE-Pub/
Project-URL: Repository, https://github.com/intellistream/SAGE.git
Project-URL: Bug Tracker, https://github.com/intellistream/SAGE/issues
Classifier: Development Status :: 4 - Beta
Classifier: Intended Audience :: Developers
Classifier: Topic :: Software Development :: Libraries :: Python Modules
Classifier: Topic :: Scientific/Engineering :: Artificial Intelligence
Classifier: Topic :: System :: Distributed Computing
Requires-Python: >=3.10
Requires-Dist: isage-common>=0.1.0
Requires-Dist: isagellm>=0.1.0
Requires-Dist: isage-platform>=0.1.0
Requires-Dist: isage-kernel>=0.1.0
Requires-Dist: isage-libs>=0.1.0
Requires-Dist: isage-middleware>=0.1.0
Provides-Extra: dev
Requires-Dist: isage[all]; extra == "dev"
Requires-Dist: isage-tools>=0.1.0; extra == "dev"
Requires-Dist: pytest>=7.4.0; extra == "dev"
Requires-Dist: pytest-cov>=4.0.0; extra == "dev"
Requires-Dist: pytest-asyncio>=0.21.0; extra == "dev"
Requires-Dist: ruff==0.14.6; extra == "dev"
Requires-Dist: mypy>=1.7.0; extra == "dev"
Requires-Dist: pre-commit>=3.5.0; extra == "dev"
Provides-Extra: all
Requires-Dist: isage-common>=0.1.0; extra == "all"
Requires-Dist: isage-platform>=0.1.0; extra == "all"
Requires-Dist: isage-kernel>=0.1.0; extra == "all"
Requires-Dist: isage-libs>=0.1.0; extra == "all"
Requires-Dist: isage-middleware>=0.1.0; extra == "all"
Requires-Dist: isage-cli>=0.1.0; extra == "all"
Requires-Dist: isage-studio>=0.1.0; extra == "all"
Requires-Dist: isagellm[gateway]>=0.1.0; extra == "all"
